foyou_sign/__init__.py
foyou_sign-0.0.2.dist-info/LICENSE
foyou_sign-0.0.2.dist-info/METADATA
foyou_sign-0.0.2.dist-info/WHEEL
foyou_sign-0.0.2.dist-info/entry_points.txt
foyou_sign-0.0.2.dist-info/top_level.txt
foyou_sign-0.0.2.dist-info/RECORD
