Metadata-Version: 2.1
Name: foyou-sign
Version: 0.0.2
Summary: python pypi package example
Home-page: https://github.com/foyoux/foyou-sign
Author: foyou
Author-email: yimi.0822@qq.com
License: GPL-3.0
Project-URL: Source, https://github.com/foyoux/foyou-sign
Project-URL: Bug Tracker, https://github.com/foyoux/foyou-sign/issues
Keywords: python pypi package example
Platform: UNKNOWN
Classifier: Programming Language :: Python :: 3
Classifier: Programming Language :: Python :: 3.7
Classifier: Programming Language :: Python :: 3.8
Classifier: Programming Language :: Python :: 3.9
Classifier: Programming Language :: Python :: 3.10
Classifier: Programming Language :: Python :: 3.11
Classifier: License :: OSI Approved :: GNU General Public License v3 (GPLv3)
Classifier: Environment :: Console
Classifier: Natural Language :: Chinese (Simplified)
Classifier: Development Status :: 4 - Beta
Requires-Python: >=3.7.*
